LICENSE.txt
MANIFEST.in
README.rst
astromatic_install.sh
depend_install.sh
post_install.sh
setup.cfg
setup.py
photopipe/VERSION
photopipe/__init__.py
photopipe/cmdline.py
photopipe.egg-info/PKG-INFO
photopipe.egg-info/SOURCES.txt
photopipe.egg-info/dependency_links.txt
photopipe.egg-info/entry_points.txt
photopipe.egg-info/top_level.txt
photopipe/instruments/__init__.py
photopipe/instruments/instrument_class.py
photopipe/instruments/specific_instruments.py
photopipe/photometry/__init__.py
photopipe/photometry/autoredux.py
photopipe/photometry/photom.py
photopipe/photometry/plotphotom.py
photopipe/photometry/printhtml.py
photopipe/photometry/defaults/ratir.conv
photopipe/photometry/defaults/ratir_nir.nnw
photopipe/photometry/defaults/ratir_nir.sex
photopipe/photometry/defaults/ratir_weighted.sex
photopipe/photometry/defaults/sex.conv
photopipe/photometry/defaults/temp.param
photopipe/photometry/defaults/weightedtemp.param
photopipe/photometry/dependencies/__init__.py
photopipe/photometry/dependencies/all_models.npy
photopipe/photometry/dependencies/default_highsnr.sex
photopipe/photometry/dependencies/err_dict.p
photopipe/photometry/dependencies/get_SEDs.py
photopipe/photometry/dependencies/get_SEDs.pyc
photopipe/photometry/dependencies/photprocesslibrary.py
photopipe/photometry/dependencies/photprocesslibrary.pyc
photopipe/photometry/dependencies/zeropoint.py
photopipe/reduction/__init__.py
photopipe/reduction/preproc.py
photopipe/reduction/astrom/__init__.py
photopipe/reduction/astrom/astrometrydist.py
photopipe/reduction/astrom/astrometrydist.pyc
photopipe/reduction/astrom/astrometrysources.py
photopipe/reduction/astrom/astrometrysources.pyc
photopipe/reduction/astrom/astrometrystats.py
photopipe/reduction/astrom/astrometrystats.pyc
photopipe/reduction/astrom/default.nnw
photopipe/reduction/astrom/sex.config
photopipe/reduction/astrom/sex.conv
photopipe/reduction/astrom/tempsource.param
photopipe/reduction/astrom/vlt_autoastrometry.py
photopipe/reduction/auto/__init__.py
photopipe/reduction/auto/autoproc.py
photopipe/reduction/auto/autoproc_depend.py
photopipe/reduction/auto/autoproc_steps.py
photopipe/reduction/auto/cosmics.py
