Metadata-Version: 1.1
Name: photopipe
Version: 0.1.0b4
Summary: PhotoPipe is a pipeline for automated reduction, photometry and astrometry of imaging data from RATIR and RIMAS.
Home-page: https://github.com/maxperry/photometrypipeline
Author: maxperry, vickitoy, cenko
Author-email: photopipe@googlegroups.com
License: GPL-3.0
Keywords: cosmology photometry reduction astrometry ratir rimas astropy
Platform: UNKNOWN
Classifier: Development Status :: 4 - Beta
Classifier: Intended Audience :: Science/Research
Classifier: Topic :: Scientific/Engineering :: Astronomy
Classifier: License :: OSI Approved :: GNU General Public License v3 (GPLv3)
Classifier: Programming Language :: Python :: 2
Classifier: Programming Language :: Python :: 2.7
